repl_from_cli/__init__.py
repl_from_cli/__main__.py
repl_from_cli/core/__init__.py
repl_from_cli/core/git/__init__.py
repl_from_cli/core/git/helper.py
repl_from_cli/core/helpers/__init__.py
repl_run_cli-1.0.1.dist-info/METADATA
repl_run_cli-1.0.1.dist-info/WHEEL
repl_run_cli-1.0.1.dist-info/entry_points.txt
repl_run_cli-1.0.1.dist-info/top_level.txt
repl_run_cli-1.0.1.dist-info/zip-safe
repl_run_cli-1.0.1.dist-info/RECORD
