Metadata-Version: 2.1
Name: repl-run-cli
Version: 1.0.1
Summary: Generate GitHub and Repl.it Repos with One Command
Home-page: https://github.com/M4cs/BabySploit
Author: Max Bridgland
Author-email: mabridgland@protonmail.com
License: UNKNOWN
Project-URL: Discord Server, https://discord.gg/C7jgQeN
Platform: UNKNOWN
Classifier: Development Status :: 4 - Beta
Classifier: Environment :: Console
Classifier: License :: OSI Approved :: GNU General Public License v3 (GPLv3)
Classifier: Programming Language :: Python
Classifier: Programming Language :: Python :: 3.6
Classifier: Programming Language :: Python :: 3.7
Classifier: Programming Language :: Python :: Implementation :: CPython
Classifier: Programming Language :: Python :: Implementation :: PyPy
Classifier: Programming Language :: Python :: Implementation :: IronPython
Classifier: Programming Language :: Python :: Implementation :: Jython
Classifier: Intended Audience :: Developers
Classifier: Intended Audience :: System Administrators
Classifier: Intended Audience :: Information Technology
Classifier: Topic :: Software Development :: Libraries :: Python Modules
Classifier: Topic :: Software Development :: Libraries
Classifier: Topic :: System :: Systems Administration
Classifier: Topic :: System :: Networking
Classifier: Topic :: Utilities
Requires-Dist: Werkzeug (==0.14.1)
Requires-Dist: setuptools (==41.4.0)
Requires-Dist: requests (==2.22.0)
Requires-Dist: PyGithub (==1.44.1)
